agct-0.2.0.dist-info/METADATA
agct-0.2.0.dist-info/WHEEL
agct-0.2.0.dist-info/licenses/LICENSE
agct/__init__.py
agct/_core.abi3.so
agct/converter.py
agct/seqref_registry.py
agct-0.2.0.dist-info/RECORD
