Metadata-Version: 2.4
Name: agct
Version: 0.2.0
Classifier: Development Status :: 3 - Alpha
Classifier: Programming Language :: Rust
Classifier: Programming Language :: Python
Classifier: Programming Language :: Python :: 3
Classifier: Programming Language :: Python :: 3 :: Only
Classifier: Programming Language :: Python :: 3.11
Classifier: Programming Language :: Python :: 3.12
Classifier: Programming Language :: Python :: 3.13
Classifier: Topic :: Scientific/Engineering :: Bio-Informatics
Classifier: Intended Audience :: Science/Research
Requires-Dist: wags-tails
Requires-Dist: pytest ; extra == 'tests'
Requires-Dist: pytest-cov ; extra == 'tests'
Requires-Dist: maturin ; extra == 'dev'
Requires-Dist: ruff==0.14.10 ; extra == 'dev'
Requires-Dist: prek>=0.2.23 ; extra == 'dev'
Provides-Extra: tests
Provides-Extra: dev
License-File: LICENSE
Summary: Another Genome Conversion Tool: Python frontend to Rust chainfile crate
Author: James Stevenson, Kori Kuzma
License-Expression: MIT
Requires-Python: >=3.11
Project-URL: Homepage, https://github.com/genomicmedlab/agct
Project-URL: Documentation, https://github.com/genomicmedlab/agct
Project-URL: Changelog, https://github.com/genomicmedlab/agct/releases
Project-URL: Source, https://github.com/genomicmedlab/agct
Project-URL: Bug Tracker, https://github.com/genomicmedlab/agct/issues
